mkdocs_ruby_plugin/__init__.py
mkdocs_ruby_plugin/plugin.py
mkdocs_ruby_plugin-0.0.3.dist-info/LICENSE
mkdocs_ruby_plugin-0.0.3.dist-info/METADATA
mkdocs_ruby_plugin-0.0.3.dist-info/WHEEL
mkdocs_ruby_plugin-0.0.3.dist-info/entry_points.txt
mkdocs_ruby_plugin-0.0.3.dist-info/top_level.txt
mkdocs_ruby_plugin-0.0.3.dist-info/RECORD
