Metadata-Version: 2.1
Name: mkdocs-ruby-plugin
Version: 0.0.3
Summary: An MkDocs plugin to add pinyin/furigana to Chinese/Japanese Kanji text.
Home-page: https://github.com/lesliezhu/mkdocs-ruby-plugin
Author: Leslie Zhu
Author-email: pythonisland@gmail.com
License: Apache-2.0
Keywords: mkdocs ruby plugin
Requires-Python: >=3.9
License-File: LICENSE
Requires-Dist: mkdocs (>=1.4.1)
